setup.py
pyhtmlex/__init__.py
pyhtmlex.egg-info/PKG-INFO
pyhtmlex.egg-info/SOURCES.txt
pyhtmlex.egg-info/dependency_links.txt
pyhtmlex.egg-info/top_level.txt
pyhtmlex/base/__init__.py
pyhtmlex/base/base.py
pyhtmlex/base/body.py
pyhtmlex/base/head.py
pyhtmlex/base/root.py
pyhtmlex/demo/__init__.py
pyhtmlex/demo/main.py
pyhtmlex/demo/remote_shell.py
pyhtmlex/demo/wiki/__init__.py
pyhtmlex/demo/wiki/manage.py
pyhtmlex/demo/wiki/blog/__init__.py
pyhtmlex/demo/wiki/blog/common.py
pyhtmlex/demo/wiki/blog/view.py
pyhtmlex/demo/wiki/wiki/__init__.py
pyhtmlex/demo/wiki/wiki/body.py
pyhtmlex/demo/wiki/wiki/settings.py
pyhtmlex/demo/wiki/wiki/urls.py
pyhtmlex/demo/wiki/wiki/view.py
pyhtmlex/demo/wiki/wiki/wsgi.py
pyhtmlex/utils/__init__.py
pyhtmlex/utils/code.py
pyhtmlex/utils/console.py
pyhtmlex/utils/md_parser.py
pyhtmlex/utils/table.py