Metadata-Version: 1.0
Name: pyhtmlex
Version: 1.1.1
Summary: A python lib to generate various html elements.
Home-page: https://github.com/alswell/PyHtmlEx
Author: Ning Zhou
Author-email: icemanzhouning@yeah.net
License: GPL
Platform: UNKNOWN
